datumsh/__init__.py
datumsh/skeleton.py
datum.sh-0.0.0.dist-info/LICENSE.txt
datum.sh-0.0.0.dist-info/METADATA
datum.sh-0.0.0.dist-info/WHEEL
datum.sh-0.0.0.dist-info/top_level.txt
datum.sh-0.0.0.dist-info/RECORD
