Metadata-Version: 2.1
Name: datum.sh
Version: 0.0.0
Summary: Placeholder
Home-page: https://github.com/pyscaffold/pyscaffold/
Author: Hao Wu
Author-email: haowu@haowu.me
License: MIT
Project-URL: Documentation, https://pyscaffold.org/
Platform: any
Classifier: Development Status :: 4 - Beta
Classifier: Programming Language :: Python
License-File: LICENSE.txt
Requires-Dist: importlib-metadata ; python_version < "3.8"
Provides-Extra: testing
Requires-Dist: setuptools ; extra == 'testing'
Requires-Dist: pytest ; extra == 'testing'
Requires-Dist: pytest-cov ; extra == 'testing'
